fastloguru/__init__.py
fastloguru/logger.py
fastloguru-0.1.0.dist-info/licenses/LICENSE
fastloguru-0.1.0.dist-info/METADATA
fastloguru-0.1.0.dist-info/WHEEL
fastloguru-0.1.0.dist-info/top_level.txt
fastloguru-0.1.0.dist-info/RECORD
