Metadata-Version: 2.4
Name: fastloguru
Version: 0.1.0
Summary: An enhanced wrapper for Loguru that supports multiple named loggers with automatic file output, tagging, and smart defaults.
Author-email: Saurabh Kumar Agarwal <s.dealyourself@gmail.com>
License-Expression: MIT
Requires-Python: >=3.7
License-File: LICENSE
Requires-Dist: loguru
Dynamic: license-file
